HISTORY.rst
LICENSE
MANIFEST.in
Makefile
README.rst
lemapp.py
requirements.txt
setup.cfg
setup.py
test_lemapp.py
lemapp.egg-info/PKG-INFO
lemapp.egg-info/SOURCES.txt
lemapp.egg-info/dependency_links.txt
lemapp.egg-info/requires.txt
lemapp.egg-info/top_level.txt